Workbook

Sheet Schedules
A1: The Kraft Heinz Company (NASDAQ: KHC)
A2: Integrated Financial Model and Projections (2026E - 2030E)
A3: Figures in millions of USD
A5: SCHEDULES | B5: 2023A | C5: 2024A | D5: 2025A | E5: 2026E | F5: 2027E | G5: 2028E | H5: 2029E | I5: 2030E
A7: 1. Net Sales
A9: North America
A10: Annual sales growth (%) | B10: 0 | C10: 0 | D10: =(D11/C11) - 1 -> -0.04896894 | E10: 0 | F10: =E10 -> 0 | G10: =F10 -> 0 | H10: =G10 -> 0 | I10: =H10 -> 0
A11: Net sales: North America | B11: 0 | C11: 19543 | D11: 18586 | E11: =D11*(1+E10) -> 18586 | F11: =E11*(1+F10) -> 18586 | G11: =F11*(1+G10) -> 18586 | H11: =G11*(1+H10) -> 18586 | I11: =H11*(1+I10) -> 18586
A13: International developed markets
A14: Annual sales growth (%) | B14: 0 | C14: 0 | D14: =(D15/C15) - 1 -> 0.0011315417 | E14: =D14 -> 0.0011315417 | F14: =E14 -> 0.0011315417 | G14: =F14 -> 0.0011315417 | H14: =G14 -> 0.0011315417 | I14: =H14 -> 0.0011315417
A15: Net sales: International developed markets | B15: 0 | C15: 3535 | D15: 3539 | E15: =D15*(1+E14) -> 3543.0045 | F15: =E15*(1+F14) -> 3547.0136 | G15: =F15*(1+G14) -> 3551.0272 | H15: =G15*(1+H14) -> 3555.0453 | I15: =H15*(1+I14) -> 3559.068
A17: Emerging markets
A18: Annual sales growth (%) | B18: 0 | C18: 0 | D18: =(D19/C19) - 1 -> 0.017702312 | E18: =D18 -> 0.017702312 | F18: =E18 -> 0.017702312 | G18: =F18 -> 0.017702312 | H18: =G18 -> 0.017702312 | I18: =H18 -> 0.017702312
A19: Net sales: Emerging markets | B19: 0 | C19: 2768 | D19: 2817 | E19: =D19*(1+E18) -> 2866.8674 | F19: =E19*(1+F18) -> 2917.6176 | G19: =F19*(1+G18) -> 2969.2662 | H19: =G19*(1+H18) -> 3021.829 | I19: =H19*(1+I18) -> 3075.3224
A21: Net sales
A22: Net sales | B22: ='Income Statement'!B6 -> 26640 | C22: =SUM(C11,C15,C19) -> 25846 | D22: =SUM(D11,D15,D19) -> 24942 | E22: =SUM(E11,E15,E19) -> 24995.872 | F22: =SUM(F11,F15,F19) -> 25050.631 | G22: =SUM(G11,G15,G19) -> 25106.293 | H22: =SUM(H11,H15,H19) -> 25162.874 | I22: =SUM(I11,I15,I19) -> 25220.39
A24: 2. Cost of Products Sold
A26: North America
A27: COGS - North America | B27: 0 | C27: 0 | D27: 0 | E27: =E11*E36 -> 12394.393 | F27: =F11*F36 -> 12394.393 | G27: =G11*G36 -> 12394.393 | H27: =H11*H36 -> 12394.393 | I27: =I11*I36 -> 12394.393
A29: International developed markets
A30: COGS - International developed markets | B30: 0 | C30: 0 | D30: 0 | E30: =E15*E36 -> 2362.7133 | F30: =F15*F36 -> 2365.3868 | G30: =G15*G36 -> 2368.0633 | H30: =H15*H36 -> 2370.7429 | I30: =I15*I36 -> 2373.4255
A32: Emerging markets
A33: COGS - Emerging markets | B33: 0 | C33: 0 | D33: 0 | E33: =E19*E36 -> 1911.8196 | F33: =F19*F36 -> 1945.6633 | G33: =G19*G36 -> 1980.106 | H33: =H19*H36 -> 2015.1585 | I33: =I19*I36 -> 2050.8314
A35: Cost of products sold (COGS)
A36: Cost of sales (%) | B36: =B37/B22 -> 0.66493994 | C36: =C37/C22 -> 0.65302174 | D36: =D37/D22 -> 0.66686713 | E36: =D36 -> 0.66686713 | F36: =E36 -> 0.66686713 | G36: =F36 -> 0.66686713 | H36: =G36 -> 0.66686713 | I36: =H36 -> 0.66686713
A37: Cost of products sold | B37: ='Income Statement'!B7 -> 17714 | C37: ='Income Statement'!C7 -> 16878 | D37: ='Income Statement'!D7 -> 16633 | E37: =SUM(E27,E30,E33) -> 16668.925 | F37: =SUM(F27,F30,F33) -> 16705.443 | G37: =SUM(G27,G30,G33) -> 16742.562 | H37: =SUM(H27,H30,H33) -> 16780.294 | I37: =SUM(I27,I30,I33) -> 16818.649
A39: 3. OpEx
A41: Operating expenses
A42: Annual growth of operating expenses (%) | B42: =B43/B22 -> 0.13858859 | C42: =C43/C22 -> 0.13990559 | D42: =D43/D22 -> 0.14722155 | E42: =D42 -> 0.14722155 | F42: =E42 -> 0.14722155 | G42: =F42 -> 0.14722155 | H42: =G42 -> 0.14722155 | I42: =H42 -> 0.14722155
A43: Selling, general and administrative expenses, excluding impairment losses | B43: ='Income Statement'!B9 -> 3692 | C43: ='Income Statement'!C9 -> 3616 | D43: ='Income Statement'!D9 -> 3672 | E43: =E42*E22 -> 3679.9311 | F43: =F42*F22 -> 3687.9929 | G43: =G42*G22 -> 3696.1875 | H43: =H42*H22 -> 3704.5175 | I43: =I42*I22 -> 3712.9851
A45: 4. Net Working Capital
A47: Cash conversion cycle accounts
A49: Trade receivables
A50: DSO (Days) | B50: 0 | C50: =(C51/'Income Statement'!C6)*360 -> 29.904821 | D50: =(D51/'Income Statement'!D6)*360 -> 32.533077 | E50: =D50 -> 32.533077 | F50: =E50 -> 32.533077 | G50: =F50 -> 32.533077 | H50: =G50 -> 32.533077 | I50: =H50 -> 32.533077
A51: Trade receivables | B51: 0 | C51: ='Balance Sheet'!C8 -> 2147 | D51: ='Balance Sheet'!D8 -> 2254 | E51: =(E50/360)*'Income Statement'!E6 -> 2258.8684 | F51: =(F50/360)*'Income Statement'!F6 -> 2263.817 | G51: =(G50/360)*'Income Statement'!G6 -> 2268.8471 | H51: =(H50/360)*'Income Statement'!H6 -> 2273.9603 | I51: =(I50/360)*'Income Statement'!I6 -> 2279.158
A53: Inventories
A54: DIO (Days) | B54: 0 | C54: =(C55/'Income Statement'!C7)*360 -> 72.008532 | D54: =(D55/'Income Statement'!D7)*360 -> 68.545662 | E54: =D54 -> 68.545662 | F54: =E54 -> 68.545662 | G54: =F54 -> 68.545662 | H54: =G54 -> 68.545662 | I54: =H54 -> 68.545662
A55: Inventories | B55: 0 | C55: ='Balance Sheet'!C9 -> 3376 | D55: ='Balance Sheet'!D9 -> 3167 | E55: =(E54/360)*'Income Statement'!E7 -> 3173.8404 | F55: =(F54/360)*'Income Statement'!F7 -> 3180.7934 | G55: =(G54/360)*'Income Statement'!G7 -> 3187.8611 | H55: =(H54/360)*'Income Statement'!H7 -> 3195.0454 | I55: =(I54/360)*'Income Statement'!I7 -> 3202.3485
A57: Accounts payable
A58: DPO (Days) | B58: 0 | C58: =(C59/'Income Statement'!C7)*360 -> 89.328119 | D58: =(D59/'Income Statement'!D7)*360 -> 93.241147 | E58: =D58 -> 93.241147 | F58: =E58 -> 93.241147 | G58: =F58 -> 93.241147 | H58: =G58 -> 93.241147 | I58: =H58 -> 93.241147
A59: Accounts payable | B59: 0 | C59: ='Balance Sheet'!C23 -> 4188 | D59: ='Balance Sheet'!D23 -> 4308 | E59: =(E58/360)*'Income Statement'!E7 -> 4317.3048 | F59: =(F58/360)*'Income Statement'!F7 -> 4326.7629 | G59: =(G58/360)*'Income Statement'!G7 -> 4336.3769 | H59: =(H58/360)*'Income Statement'!H7 -> 4346.1496 | I59: =(I58/360)*'Income Statement'!I7 -> 4356.0838
A61: Other operating current accounts
A63: Prepaid expenses
A64: Prepaid expenses (% of sales) | B64: 0 | C64: ='Balance Sheet'!C10/'Income Statement'!C6 -> 0.0083185019 | D64: ='Balance Sheet'!D10/'Income Statement'!D6 -> 0.011667068 | E64: =(D64+C64)/2 -> 0.0099927847 | F64: =E64 -> 0.0099927847 | G64: =F64 -> 0.0099927847 | H64: =G64 -> 0.0099927847 | I64: =H64 -> 0.0099927847
A66: Marketing expenses accrued
A67: Accrued marketing (% of sales) | B67: 0 | C67: ='Balance Sheet'!C24/'Income Statement'!C6 -> 0.026967422 | D67: ='Balance Sheet'!D24/'Income Statement'!D6 -> 0.032114506 | E67: =(D67+C67)/2 -> 0.029540964 | F67: =E67 -> 0.029540964 | G67: =F67 -> 0.029540964 | H67: =G67 -> 0.029540964 | I67: =H67 -> 0.029540964
A69: 5. CapEx, D&A & PP&E
A71: Capital expenditures
A72: CapEx (% of sales) | B72: =B73/'Income Statement'!B6 -> 0.038025526 | C72: =C73/'Income Statement'!C6 -> 0.039619283 | D72: =D73/'Income Statement'!D6 -> 0.032114506 | E72: =(D72+C72+B72)/3 -> 0.036586438 | F72: =E72 -> 0.036586438 | G72: =F72 -> 0.036586438 | H72: =G72 -> 0.036586438 | I72: =H72 -> 0.036586438
A73: Capital expenditures | B73: =-'Cash Flow Statement'!B21 -> 1013 | C73: =-'Cash Flow Statement'!C21 -> 1024 | D73: =-'Cash Flow Statement'!D21 -> 801 | E73: ='Income Statement'!E6*E72 -> 914.50992 | F73: ='Income Statement'!F6*F72 -> 916.51337 | G73: ='Income Statement'!G6*G72 -> 918.54985 | H73: ='Income Statement'!H6*H72 -> 920.61995 | I73: ='Income Statement'!I6*I72 -> 922.72426
A75: Depreciation and amortization
A76: D&A (% of sales) | B76: =B77/'Income Statement'!B6 -> 0.036073574 | C76: =C77/'Income Statement'!C6 -> 0.03667879 | D76: =D77/'Income Statement'!D6 -> 0.038810039 | E76: =(D76+C76+B76)/3 -> 0.037187468 | F76: =E76 -> 0.037187468 | G76: =F76 -> 0.037187468 | H76: =G76 -> 0.037187468 | I76: =H76 -> 0.037187468
A77: Depreciation and amortization | B77: ='Cash Flow Statement'!B9 -> 961 | C77: ='Cash Flow Statement'!C9 -> 948 | D77: ='Cash Flow Statement'!D9 -> 968 | E77: ='Income Statement'!E6*E76 -> 929.53318 | F77: ='Income Statement'!F6*F76 -> 931.56953 | G77: ='Income Statement'!G6*G76 -> 933.63947 | H77: ='Income Statement'!H6*H76 -> 935.74357 | I77: ='Income Statement'!I6*I76 -> 937.88245
A79: PP&E roll-forward
A80: Initial PP&E balance | B80: 0 | C80: 0 | D80: 0 | E80: =D83 -> 7318 | F80: =E83 -> 7302.9767 | G80: =F83 -> 7287.9206 | H80: =G83 -> 7272.831 | I80: =H83 -> 7257.7073
A81: (+) CapEx | B81: 0 | C81: 0 | D81: 0 | E81: =E73 -> 914.50992 | F81: =F73 -> 916.51337 | G81: =G73 -> 918.54985 | H81: =H73 -> 920.61995 | I81: =I73 -> 922.72426
A82: (-) D&A | B82: 0 | C82: 0 | D82: 0 | E82: =-E77 -> -929.53318 | F82: =-F77 -> -931.56953 | G82: =-G77 -> -933.63947 | H82: =-H77 -> -935.74357 | I82: =-I77 -> -937.88245
A83: Final PP&E balance, net | B83: 0 | C83: ='Balance Sheet'!C15 -> 7152 | D83: ='Balance Sheet'!D15 -> 7318 | E83: =SUM(E80:E82) -> 7302.9767 | F83: =SUM(F80:F82) -> 7287.9206 | G83: =SUM(G80:G82) -> 7272.831 | H83: =SUM(H80:H82) -> 7257.7073 | I83: =SUM(I80:I82) -> 7242.5491
A85: 6. Debt & Interest
A87: Debt roll-forward
A88: Initial debt balance | B88: 0 | C88: 0 | D88: =C92 -> 19869 | E88: =D92 -> 21219 | F88: =E92 -> 21219 | G88: =F92 -> 21219 | H88: =G92 -> 21219 | I88: =H92 -> 21219
A89: (+) Proceeds from issuance of long-term debt | B89: 0 | C89: 0 | D89: ='Cash Flow Statement'!D27 -> 1620 | E89: 1900 | F89: 0 | G89: =F89 -> 0 | H89: =G89 -> 0 | I89: =H89 -> 0
A90: (-) Repayments of long-term debt | B90: 0 | C90: 0 | D90: ='Cash Flow Statement'!D26 -> -678 | E90: -1900 | F90: 0 | G90: =F90 -> 0 | H90: =G90 -> 0 | I90: =H90 -> 0
A91: (+/-) Adjustments (FX effect and others) | B91: 0 | C91: 0 | D91: =D92-SUM(D88:D90) -> 408 | E91: 0 | F91: =E91 -> 0 | G91: =F91 -> 0 | H91: =G91 -> 0 | I91: =H91 -> 0
A92: Final debt balance | B92: 0 | C92: ='Balance Sheet'!C29+'Balance Sheet'!C22 -> 19869 | D92: ='Balance Sheet'!D29+'Balance Sheet'!D22 -> 21219 | E92: =SUM(E88:E91) -> 21219 | F92: =SUM(F88:F91) -> 21219 | G92: =SUM(G88:G91) -> 21219 | H92: =SUM(H88:H91) -> 21219 | I92: =SUM(I88:I91) -> 21219
A94: Current portion of debt (% of final debt balance) | B94: 0 | C94: ='Balance Sheet'!C22/C92 -> 0.032915597 | D94: ='Balance Sheet'!D22/D92 -> 0.089919412 | E94: =D94 -> 0.089919412 | F94: =E94 -> 0.089919412 | G94: =F94 -> 0.089919412 | H94: =G94 -> 0.089919412 | I94: =H94 -> 0.089919412
A95: Current portion of long-term debt | B95: 0 | C95: =C92*C94 -> 654 | D95: =D92*D94 -> 1908 | E95: =E92*E94 -> 1908 | F95: =F92*F94 -> 1908 | G95: =G92*G94 -> 1908 | H95: =H92*H94 -> 1908 | I95: =I92*I94 -> 1908
A96: Long-term debt | B96: 0 | C96: =C92-C95 -> 19215 | D96: =D92-D95 -> 19311 | E96: =E92-E95 -> 19311 | F96: =F92-F95 -> 19311 | G96: =G92-G95 -> 19311 | H96: =H92-H95 -> 19311 | I96: =I92-I95 -> 19311
A98: Interest expenses
A99: Average total debt | B99: 0 | C99: 0 | D99: =(D88+D92)/2 -> 20544 | E99: =(E88+E92)/2 -> 21219 | F99: =(F88+F92)/2 -> 21219 | G99: =(G88+G92)/2 -> 21219 | H99: =(H88+H92)/2 -> 21219 | I99: =(I88+I92)/2 -> 21219
A100: Implied interest rate | B100: 0 | C100: 0 | D100: =D101/D99 -> 0.046096184 | E100: =D100 -> 0.046096184 | F100: =E100 -> 0.046096184 | G100: =F100 -> 0.046096184 | H100: =G100 -> 0.046096184 | I100: =H100 -> 0.046096184
A101: Interest expense | B101: 0 | C101: ='Income Statement'!C14 -> 912 | D101: ='Income Statement'!D14 -> 947 | E101: =E99*E100 -> 978.11492 | F101: =F99*F100 -> 978.11492 | G101: =G99*G100 -> 978.11492 | H101: =H99*H100 -> 978.11492 | I101: =I99*I100 -> 978.11492
A103: Interest payable
A104: Interest payable (% of interest expense) | B104: 0 | C104: ='Balance Sheet'!C25/'Income Statement'!C14 -> 0.28837719 | D104: ='Balance Sheet'!D25/'Income Statement'!D14 -> 0.31467793 | E104: =(D104+C104)/2 -> 0.30152756 | F104: =E104 -> 0.30152756 | G104: =F104 -> 0.30152756 | H104: =G104 -> 0.30152756 | I104: =H104 -> 0.30152756
A106: 7. Tax Rate
A108: U.S. statutory tax rate adjustment
A109: Effective tax rate | B109: ='Income Statement'!B17/'Income Statement'!B16 -> 0.21662538 | C109: ='Income Statement'!C17/'Income Statement'!C16 -> -2.2079439 | D109: ='Income Statement'!D17/'Income Statement'!D16 -> -0.074012856 | E109: 0.21 | F109: =E109 -> 0.21 | G109: =F109 -> 0.21 | H109: =G109 -> 0.21 | I109: =H109 -> 0.21
A111: 8. Retained Earnings
A113: Dividends declared-common stock
A114: Dividends declared-common stock | B114: 0 | C114: -1940 | D114: -1906 | E114: 0 | F114: 0 | G114: 0 | H114: 0 | I114: 0
A116: Retained earnings roll-forward
A117: Initial retained earnings balance | B117: 0 | C117: 0 | D117: =C120 -> 2171 | E117: =D120 -> -4629 | F117: =E120 -> -3636.5686 | G117: =F120 -> -2636.0948 | H117: =G120 -> -1627.4458 | I117: =H120 -> -610.48678
A118: (+) Net income/(loss) attributable to common shareholders | B118: 0 | C118: 0 | D118: ='Income Statement'!D20 -> -5846 | E118: ='Income Statement'!E20 -> 2898.4314 | F118: ='Income Statement'!F20 -> 2906.4739 | G118: ='Income Statement'!G20 -> 2914.649 | H118: ='Income Statement'!H20 -> 2922.959 | I118: ='Income Statement'!I20 -> 2931.4064
A119: (-) Dividends declared | B119: 0 | C119: 0 | D119: =D120-SUM(D117:D118) -> -954 | E119: =D114 -> -1906 | F119: =E119 -> -1906 | G119: =F119 -> -1906 | H119: =G119 -> -1906 | I119: =H119 -> -1906
A120: Final retained earnings balance | B120: 0 | C120: ='Balance Sheet'!C40 -> 2171 | D120: ='Balance Sheet'!D40 -> -4629 | E120: =SUM(E117:E119) -> -3636.5686 | F120: =SUM(F117:F119) -> -2636.0948 | G120: =SUM(G117:G119) -> -1627.4458 | H120: =SUM(H117:H119) -> -610.48678 | I120: =SUM(I117:I119) -> 414.91961
A122: 9. Other Cash Flow Items
A124: Other non-cash items (Historical plug)
A125: Divestiture-related license income | B125: -54 | C125: -54 | D125: -52 | E125: 0 | F125: =E125 -> 0 | G125: =F125 -> 0 | H125: =G125 -> 0 | I125: =H125 -> 0
A126: Equity award compensation expense | B126: 141 | C126: 109 | D126: 95 | E126: 0 | F126: =E126 -> 0 | G126: =F126 -> 0 | H126: =G126 -> 0 | I126: =H126 -> 0
A127: Deferred income tax provision/(benefit) | B127: 17 | C127: -2857 | D127: -495 | E127: 0 | F127: =E127 -> 0 | G127: =F127 -> 0 | H127: =G127 -> 0 | I127: =H127 -> 0
A128: Postemployment benefit plan asset transfers/(contributions) | B128: -22 | C128: 161 | D128: 185 | E128: 0 | F128: =E128 -> 0 | G128: =F128 -> 0 | H128: =G128 -> 0 | I128: =H128 -> 0
A129: Goodwill and intangible asset impairment losses | B129: 662 | C129: 3669 | D129: 9306 | E129: 0 | F129: =E129 -> 0 | G129: =F129 -> 0 | H129: =G129 -> 0 | I129: =H129 -> 0
A130: Nonmonetary currency devaluation | B130: 28 | C130: 16 | D130: 34 | E130: 0 | F130: =E130 -> 0 | G130: =F130 -> 0 | H130: =G130 -> 0 | I130: =H130 -> 0
A131: Loss/(gain) on sale of business | B131: -4 | C131: 81 | D131: 42 | E131: 0 | F131: =E131 -> 0 | G131: =F131 -> 0 | H131: =G131 -> 0 | I131: =H131 -> 0
A132: Other items, net | B132: 207 | C132: -46 | D132: -3 | E132: 0 | F132: =E132 -> 0 | G132: =F132 -> 0 | H132: =G132 -> 0 | I132: =H132 -> 0
A134: Other NWC items (Historical plug)
A135: Other current assets | B135: 139 | C135: -38 | D135: -88 | E135: 0 | F135: =E135 -> 0 | G135: =F135 -> 0 | H135: =G135 -> 0 | I135: =H135 -> 0
A136: Other current liabilities | B136: -562 | C136: -98 | D136: 337 | E136: 0 | F136: =E136 -> 0 | G136: =F136 -> 0 | H136: =G136 -> 0 | I136: =H136 -> 0
A138: Other investing activities (Historical plug)
A139: Payments to acquire intangible assets | B139: 0 | C139: -140 | D139: 0 | E139: 0 | F139: =E139 -> 0 | G139: =F139 -> 0 | H139: =G139 -> 0 | I139: =H139 -> 0
...

Sheet Income Statement
A1: The Kraft Heinz Company (NASDAQ: KHC)
A2: Integrated Financial Model and Projections (2026E - 2030E)
A3: Figures in millions of USD
A5: INCOME STATEMENT | B5: 2023A | C5: 2024A | D5: 2025A | E5: 2026E | F5: 2027E | G5: 2028E | H5: 2029E | I5: 2030E
A6: Net sales | B6: 26640 | C6: =Schedules!C22 -> 25846 | D6: =Schedules!D22 -> 24942 | E6: =Schedules!E22 -> 24995.872 | F6: =Schedules!F22 -> 25050.631 | G6: =Schedules!G22 -> 25106.293 | H6: =Schedules!H22 -> 25162.874 | I6: =Schedules!I22 -> 25220.39
A7: Cost of products sold | B7: 17714 | C7: 16878 | D7: 16633 | E7: =Schedules!E37 -> 16668.925 | F7: =Schedules!F37 -> 16705.443 | G7: =Schedules!G37 -> 16742.562 | H7: =Schedules!H37 -> 16780.294 | I7: =Schedules!I37 -> 16818.649
A8: Gross profit | B8: =B6-B7 -> 8926 | C8: =C6-C7 -> 8968 | D8: =D6-D7 -> 8309 | E8: =E6-E7 -> 8326.9465 | F8: =F6-F7 -> 8345.1886 | G8: =G6-G7 -> 8363.7315 | H8: =H6-H7 -> 8382.5805 | I8: =I6-I7 -> 8401.741
A9: Selling, general and administrative expenses, excluding impairment losses | B9: 3692 | C9: 3616 | D9: 3672 | E9: =Schedules!E43 -> 3679.9311 | F9: =Schedules!F43 -> 3687.9929 | G9: =Schedules!G43 -> 3696.1875 | H9: =Schedules!H43 -> 3704.5175 | I9: =Schedules!I43 -> 3712.9851
A10: Goodwill impairment losses | B10: 510 | C10: 1638 | D10: 6734 | E10: 0 | F10: =E10 -> 0 | G10: =F10 -> 0 | H10: =G10 -> 0 | I10: =H10 -> 0
A11: Intangible asset impairment losses | B11: 152 | C11: 2031 | D11: 2572 | E11: 0 | F11: =E11 -> 0 | G11: =F11 -> 0 | H11: =G11 -> 0 | I11: =H11 -> 0
A12: Selling, general and administrative expenses (Total) | B12: =SUM(B9:B11) -> 4354 | C12: =SUM(C9:C11) -> 7285 | D12: =SUM(D9:D11) -> 12978 | E12: =SUM(E9:E11) -> 3679.9311 | F12: =SUM(F9:F11) -> 3687.9929 | G12: =SUM(G9:G11) -> 3696.1875 | H12: =SUM(H9:H11) -> 3704.5175 | I12: =SUM(I9:I11) -> 3712.9851
A13: Operating income/(loss) | B13: =B8-B12 -> 4572 | C13: =C8-C12 -> 1683 | D13: =D8-D12 -> -4669 | E13: =E8-E12 -> 4647.0154 | F13: =F8-F12 -> 4657.1958 | G13: =G8-G12 -> 4667.544 | H13: =H8-H12 -> 4678.063 | I13: =I8-I12 -> 4688.7559
A14: Interest expense | B14: 912 | C14: 912 | D14: 947 | E14: =Schedules!E101 -> 978.11492 | F14: =Schedules!F101 -> 978.11492 | G14: =Schedules!G101 -> 978.11492 | H14: =Schedules!H101 -> 978.11492 | I14: =Schedules!I101 -> 978.11492
A15: Other expense/(income) | B15: 27 | C15: -85 | D15: -171 | E15: 0 | F15: =E15 -> 0 | G15: =F15 -> 0 | H15: =G15 -> 0 | I15: =H15 -> 0
A16: Income/(loss) before income taxes | B16: =B13-B14-B15 -> 3633 | C16: =C13-C14-C15 -> 856 | D16: =D13-D14-D15 -> -5445 | E16: =E13-E14-E15 -> 3668.9005 | F16: =F13-F14-F15 -> 3679.0808 | G16: =G13-G14-G15 -> 3689.4291 | H16: =H13-H14-H15 -> 3699.9481 | I16: =I13-I14-I15 -> 3710.641
A17: Provision for/(benefit from) income taxes | B17: 787 | C17: -1890 | D17: 403 | E17: =E16*Schedules!E109 -> 770.4691 | F17: =F16*Schedules!F109 -> 772.60698 | G17: =G16*Schedules!G109 -> 774.7801 | H17: =H16*Schedules!H109 -> 776.9891 | I17: =I16*Schedules!I109 -> 779.23461
A18: Net income/(loss) | B18: =B16-B17 -> 2846 | C18: =C16-C17 -> 2746 | D18: =D16-D17 -> -5848 | E18: =E16-E17 -> 2898.4314 | F18: =F16-F17 -> 2906.4739 | G18: =G16-G17 -> 2914.649 | H18: =H16-H17 -> 2922.959 | I18: =I16-I17 -> 2931.4064
A19: Net income/(loss) attributable to noncontrolling interest | B19: -9 | C19: 2 | D19: -2 | E19: 0 | F19: =E19 -> 0 | G19: =F19 -> 0 | H19: =G19 -> 0 | I19: =H19 -> 0
A20: Net income/(loss) attributable to common shareholders | B20: =B18-B19 -> 2855 | C20: =C18-C19 -> 2744 | D20: =D18-D19 -> -5846 | E20: =E18-E19 -> 2898.4314 | F20: =F18-F19 -> 2906.4739 | G20: =G18-G19 -> 2914.649 | H20: =H18-H19 -> 2922.959 | I20: =I18-I19 -> 2931.4064

Sheet Balance Sheet
A1: The Kraft Heinz Company (NASDAQ: KHC)
A2: Integrated Financial Model and Projections (2026E - 2030E)
A3: Figures in millions of USD
A5: BALANCE SHEET | B5: 2023A | C5: 2024A | D5: 2025A | E5: 2026E | F5: 2027E | G5: 2028E | H5: 2029E | I5: 2030E
A6: Assets
A7: Cash and cash equivalents | B7: 0 | C7: 1334 | D7: 2615 | E7: ='Cash Flow Statement'!E37-Schedules!E152 -> 3587.6031 | F7: ='Cash Flow Statement'!F37-Schedules!F152 -> 4601.76 | G7: ='Cash Flow Statement'!G37-Schedules!G152 -> 5624.1028 | H7: ='Cash Flow Statement'!H37-Schedules!H152 -> 6654.7667 | I7: ='Cash Flow Statement'!I37-Schedules!I152 -> 7693.889
A8: Trade receivables | B8: 0 | C8: 2147 | D8: 2254 | E8: =Schedules!E51 -> 2258.8684 | F8: =Schedules!F51 -> 2263.817 | G8: =Schedules!G51 -> 2268.8471 | H8: =Schedules!H51 -> 2273.9603 | I8: =Schedules!I51 -> 2279.158
A9: Inventories | B9: 0 | C9: 3376 | D9: 3167 | E9: =Schedules!E55 -> 3173.8404 | F9: =Schedules!F55 -> 3180.7934 | G9: =Schedules!G55 -> 3187.8611 | H9: =Schedules!H55 -> 3195.0454 | I9: =Schedules!I55 -> 3202.3485
A10: Prepaid expenses | B10: 0 | C10: 215 | D10: 291 | E10: ='Income Statement'!E6*Schedules!E64 -> 249.77837 | F10: ='Income Statement'!F6*Schedules!F64 -> 250.32557 | G10: ='Income Statement'!G6*Schedules!G64 -> 250.88179 | H10: ='Income Statement'!H6*Schedules!H64 -> 251.44719 | I10: ='Income Statement'!I6*Schedules!I64 -> 252.02193
A11: Marketable securities | B11: 0 | C11: 0 | D11: 1060 | E11: =D11 -> 1060 | F11: =E11 -> 1060 | G11: =F11 -> 1060 | H11: =G11 -> 1060 | I11: =H11 -> 1060
A12: Other current assets | B12: 0 | C12: 583 | D12: 588 | E12: =D12 -> 588 | F12: =E12 -> 588 | G12: =F12 -> 588 | H12: =G12 -> 588 | I12: =H12 -> 588
A13: Assets held for sale | B13: 0 | C13: 0 | D13: 152 | E13: =D13 -> 152 | F13: =E13 -> 152 | G13: =F13 -> 152 | H13: =G13 -> 152 | I13: =H13 -> 152
A14: Total current assets | B14: 0 | C14: =SUM(C7:C13) -> 7655 | D14: =SUM(D7:D13) -> 10127 | E14: =SUM(E7:E13) -> 11070.09 | F14: =SUM(F7:F13) -> 12096.696 | G14: =SUM(G7:G13) -> 13131.693 | H14: =SUM(H7:H13) -> 14175.22 | I14: =SUM(I7:I13) -> 15227.418
A15: Property, plant and equipment, net | B15: 0 | C15: 7152 | D15: 7318 | E15: =Schedules!E83 -> 7302.9767 | F15: =Schedules!F83 -> 7287.9206 | G15: =Schedules!G83 -> 7272.831 | H15: =Schedules!H83 -> 7257.7073 | I15: =Schedules!I83 -> 7242.5491
A16: Goodwill | B16: 0 | C16: 28673 | D16: 22179 | E16: =D16 -> 22179 | F16: =E16 -> 22179 | G16: =F16 -> 22179 | H16: =G16 -> 22179 | I16: =H16 -> 22179
A17: Intangible assets, net | B17: 0 | C17: 40099 | D17: 37529 | E17: =D17 -> 37529 | F17: =E17 -> 37529 | G17: =F17 -> 37529 | H17: =G17 -> 37529 | I17: =H17 -> 37529
A18: Other non-current assets | B18: 0 | C18: 4708 | D18: 4633 | E18: =D18 -> 4633 | F18: =E18 -> 4633 | G18: =F18 -> 4633 | H18: =G18 -> 4633 | I18: =H18 -> 4633
A19: Total assets | B19: 0 | C19: =SUM(C14:C18) -> 88287 | D19: =SUM(D14:D18) -> 81786 | E19: =SUM(E14:E18) -> 82714.067 | F19: =SUM(F14:F18) -> 83725.617 | G19: =SUM(G14:G18) -> 84745.524 | H19: =SUM(H14:H18) -> 85773.927 | I19: =SUM(I14:I18) -> 86810.967
A21: Liabilities
A22: Current portion of long-term debt | B22: 0 | C22: 654 | D22: 1908 | E22: =Schedules!E95 -> 1908 | F22: =Schedules!F95 -> 1908 | G22: =Schedules!G95 -> 1908 | H22: =Schedules!H95 -> 1908 | I22: =Schedules!I95 -> 1908
A23: Accounts payable | B23: 0 | C23: 4188 | D23: 4308 | E23: =Schedules!E59 -> 4317.3048 | F23: =Schedules!F59 -> 4326.7629 | G23: =Schedules!G59 -> 4336.3769 | H23: =Schedules!H59 -> 4346.1496 | I23: =Schedules!I59 -> 4356.0838
A24: Accrued marketing | B24: 0 | C24: 697 | D24: 801 | E24: ='Income Statement'!E6*Schedules!E67 -> 738.40215 | F24: ='Income Statement'!F6*Schedules!F67 -> 740.01979 | G24: ='Income Statement'!G6*Schedules!G67 -> 741.66411 | H24: ='Income Statement'!H6*Schedules!H67 -> 743.33557 | I24: ='Income Statement'!I6*Schedules!I67 -> 745.03465
A25: Interest payable | B25: 0 | C25: 263 | D25: 298 | E25: ='Income Statement'!E14*Schedules!E104 -> 294.92861 | F25: ='Income Statement'!F14*Schedules!F104 -> 294.92861 | G25: ='Income Statement'!G14*Schedules!G104 -> 294.92861 | H25: ='Income Statement'!H14*Schedules!H104 -> 294.92861 | I25: ='Income Statement'!I14*Schedules!I104 -> 294.92861
A26: Other current liabilities | B26: 0 | C26: 1451 | D26: 1455 | E26: =D26 -> 1455 | F26: =E26 -> 1455 | G26: =F26 -> 1455 | H26: =G26 -> 1455 | I26: =H26 -> 1455
A27: Liabilities held for sale | B27: 0 | C27: 0 | D27: 8 | E27: 0 | F27: =E27 -> 0 | G27: =F27 -> 0 | H27: =G27 -> 0 | I27: =H27 -> 0
A28: Total current liabilities | B28: 0 | C28: =SUM(C22:C27) -> 7253 | D28: =SUM(D22:D27) -> 8778 | E28: =SUM(E22:E27) -> 8713.6356 | F28: =SUM(F22:F27) -> 8724.7113 | G28: =SUM(G22:G27) -> 8735.9696 | H28: =SUM(H22:H27) -> 8747.4138 | I28: =SUM(I22:I27) -> 8759.047
A29: Long-term debt | B29: 0 | C29: 19215 | D29: 19311 | E29: =Schedules!E96 -> 19311 | F29: =Schedules!F96 -> 19311 | G29: =Schedules!G96 -> 19311 | H29: =Schedules!H96 -> 19311 | I29: =Schedules!I96 -> 19311
A30: Deferred income taxes | B30: 0 | C30: 9679 | D30: 9022 | E30: =D30 -> 9022 | F30: =E30 -> 9022 | G30: =F30 -> 9022 | H30: =G30 -> 9022 | I30: =H30 -> 9022
A31: Accrued postemployment costs | B31: 0 | C31: 135 | D31: 131 | E31: =D31 -> 131 | F31: =E31 -> 131 | G31: =F31 -> 131 | H31: =G31 -> 131 | I31: =H31 -> 131
A32: Long-term deferred income | B32: 0 | C32: 1374 | D32: 1321 | E32: =D32 -> 1321 | F32: =E32 -> 1321 | G32: =F32 -> 1321 | H32: =G32 -> 1321 | I32: =H32 -> 1321
A33: Other non-current liabilities | B33: 0 | C33: 1306 | D33: 1434 | E33: =D33 -> 1434 | F33: =E33 -> 1434 | G33: =F33 -> 1434 | H33: =G33 -> 1434 | I33: =H33 -> 1434
A34: Total liabilities | B34: 0 | C34: =SUM(C28:C33) -> 38962 | D34: =SUM(D28:D33) -> 39997 | E34: =SUM(E28:E33) -> 39932.636 | F34: =SUM(F28:F33) -> 39943.711 | G34: =SUM(G28:G33) -> 39954.97 | H34: =SUM(H28:H33) -> 39966.414 | I34: =SUM(I28:I33) -> 39978.047
A35: Redeemable noncontrolling interest | B35: 0 | C35: 6 | D35: 12 | E35: =D35 -> 12 | F35: =E35 -> 12 | G35: =F35 -> 12 | H35: =G35 -> 12 | I35: =H35 -> 12
A37: Equity
A38: Common stock | B38: 0 | C38: 12 | D38: 12 | E38: =D38 -> 12 | F38: =E38 -> 12 | G38: =F38 -> 12 | H38: =G38 -> 12 | I38: =H38 -> 12
A39: Additional paid-in capital | B39: 0 | C39: 52135 | D39: 51287 | E39: =D39 -> 51287 | F39: =E39 -> 51287 | G39: =F39 -> 51287 | H39: =G39 -> 51287 | I39: =H39 -> 51287
A40: Retained earnings/(deficit) | B40: 0 | C40: 2171 | D40: -4629 | E40: =Schedules!E120 -> -3636.5686 | F40: =Schedules!F120 -> -2636.0948 | G40: =Schedules!G120 -> -1627.4458 | H40: =Schedules!H120 -> -610.48678 | I40: =Schedules!I120 -> 414.91961
A41: Accumulated other comprehensive income/(losses) | B41: 0 | C41: -2915 | D41: -2370 | E41: =D41 -> -2370 | F41: =E41 -> -2370 | G41: =F41 -> -2370 | H41: =G41 -> -2370 | I41: =H41 -> -2370
A42: Treasury stock, at cost | B42: 0 | C42: -2218 | D42: -2636 | E42: =D42 -> -2636 | F42: =E42 -> -2636 | G42: =F42 -> -2636 | H42: =G42 -> -2636 | I42: =H42 -> -2636
A43: Total shareholders' equity | B43: 0 | C43: =SUM(C38:C42) -> 49185 | D43: =SUM(D38:D42) -> 41664 | E43: =SUM(E38:E42) -> 42656.431 | F43: =SUM(F38:F42) -> 43656.905 | G43: =SUM(G38:G42) -> 44665.554 | H43: =SUM(H38:H42) -> 45682.513 | I43: =SUM(I38:I42) -> 46707.92
A44: Noncontrolling interest | B44: 0 | C44: 134 | D44: 113 | E44: =D44 -> 113 | F44: =E44 -> 113 | G44: =F44 -> 113 | H44: =G44 -> 113 | I44: =H44 -> 113
A45: Total equity | B45: 0 | C45: =SUM(C43:C44) -> 49319 | D45: =SUM(D43:D44) -> 41777 | E45: =SUM(E43:E44) -> 42769.431 | F45: =SUM(F43:F44) -> 43769.905 | G45: =SUM(G43:G44) -> 44778.554 | H45: =SUM(H43:H44) -> 45795.513 | I45: =SUM(I43:I44) -> 46820.92
A47: Total liabilities and equity | B47: 0 | C47: =C34+C45+C35 -> 88287 | D47: =D34+D45+D35 -> 81786 | E47: =E34+E45+E35 -> 82714.067 | F47: =F34+F45+F35 -> 83725.617 | G47: =G34+G45+G35 -> 84745.524 | H47: =H34+H45+H35 -> 85773.927 | I47: =I34+I45+I35 -> 86810.967
A49: Balance Check (Assets - Liab. & Equity) | B49: 0 | C49: =ROUND(C19-C47, 2) -> 0 | D49: =ROUND(D19-D47, 2) -> 0 | E49: =ROUND(E19-E47, 2) -> 0 | F49: =ROUND(F19-F47, 2) -> 0 | G49: =ROUND(G19-G47, 2) -> 0 | H49: =ROUND(H19-H47, 2) -> 0 | I49: =ROUND(I19-I47, 2) -> 0

Sheet Cash Flow Statement
A1: The Kraft Heinz Company (NASDAQ: KHC)
A2: Integrated Financial Model and Projections (2026E - 2030E)
A3: Figures in millions of USD
A5: CASH FLOW STATEMENT | B5: 2023A | C5: 2024A | D5: 2025A | E5: 2026E | F5: 2027E | G5: 2028E | H5: 2029E | I5: 2030E
A6: Cash flows from operating activities
A7: Net income/(loss) | B7: ='Income Statement'!B18 -> 2846 | C7: ='Income Statement'!C18 -> 2746 | D7: ='Income Statement'!D18 -> -5848 | E7: ='Income Statement'!E18 -> 2898.4314 | F7: ='Income Statement'!F18 -> 2906.4739 | G7: ='Income Statement'!G18 -> 2914.649 | H7: ='Income Statement'!H18 -> 2922.959 | I7: ='Income Statement'!I18 -> 2931.4064
A8: Adjustments to reconcile net income to operating cash flows
A9: Depreciation and amortization | B9: 961 | C9: 948 | D9: 968 | E9: =Schedules!E77 -> 929.53318 | F9: =Schedules!F77 -> 931.56953 | G9: =Schedules!G77 -> 933.63947 | H9: =Schedules!H77 -> 935.74357 | I9: =Schedules!I77 -> 937.88245
A10: Other non-cash items (Historical plug) | B10: =SUM(Schedules!B125:B132) -> 975 | C10: =SUM(Schedules!C125:C132) -> 1079 | D10: =SUM(Schedules!D125:D132) -> 9112 | E10: =SUM(Schedules!E125:E132) -> 0 | F10: =SUM(Schedules!F125:F132) -> 0 | G10: =SUM(Schedules!G125:G132) -> 0 | H10: =SUM(Schedules!H125:H132) -> 0 | I10: =SUM(Schedules!I125:I132) -> 0
A11: Changes in current assets and liabilities
A12: Trade receivables | B12: 18 | C12: -139 | D12: -55 | E12: ='Balance Sheet'!D8-'Balance Sheet'!E8 -> -4.8683887 | F12: ='Balance Sheet'!E8-'Balance Sheet'!F8 -> -4.9485737 | G12: ='Balance Sheet'!F8-'Balance Sheet'!G8 -> -5.0301714 | H12: ='Balance Sheet'!G8-'Balance Sheet'!H8 -> -5.1132067 | I12: ='Balance Sheet'!H8-'Balance Sheet'!I8 -> -5.1977051
A13: Inventories | B13: -106 | C13: -6 | D13: 133 | E13: ='Balance Sheet'!D9-'Balance Sheet'!E9 -> -6.8403669 | F13: ='Balance Sheet'!E9-'Balance Sheet'!F9 -> -6.9530315 | G13: ='Balance Sheet'!F9-'Balance Sheet'!G9 -> -7.0676809 | H13: ='Balance Sheet'!G9-'Balance Sheet'!H9 -> -7.1843503 | I13: ='Balance Sheet'!H9-'Balance Sheet'!I9 -> -7.3030755
A14: Accounts payable | B14: -295 | C14: -308 | D14: -97 | E14: ='Balance Sheet'!E23-'Balance Sheet'!D23 -> 9.3047997 | F14: ='Balance Sheet'!F23-'Balance Sheet'!E23 -> 9.4580548 | G14: ='Balance Sheet'!G23-'Balance Sheet'!F23 -> 9.6140099 | H14: ='Balance Sheet'!H23-'Balance Sheet'!G23 -> 9.7727127 | I14: ='Balance Sheet'!I23-'Balance Sheet'!H23 -> 9.9342119
A15: Prepaid expenses | B15: 0 | C15: 0 | D15: 0 | E15: ='Balance Sheet'!D10-'Balance Sheet'!E10 -> 41.221632 | F15: ='Balance Sheet'!E10-'Balance Sheet'!F10 -> -0.54719729 | G15: ='Balance Sheet'!F10-'Balance Sheet'!G10 -> -0.5562201 | H15: ='Balance Sheet'!G10-'Balance Sheet'!H10 -> -0.56540187 | I15: ='Balance Sheet'!H10-'Balance Sheet'!I10 -> -0.57474544
A16: Accrued marketing | B16: 0 | C16: 0 | D16: 0 | E16: ='Balance Sheet'!E24-'Balance Sheet'!D24 -> -62.597846 | F16: ='Balance Sheet'!F24-'Balance Sheet'!E24 -> 1.6176407 | G16: ='Balance Sheet'!G24-'Balance Sheet'!F24 -> 1.6443142 | H16: ='Balance Sheet'!H24-'Balance Sheet'!G24 -> 1.6714576 | I16: ='Balance Sheet'!I24-'Balance Sheet'!H24 -> 1.6990794
A17: Other NWC items (Historical plug) | B17: =SUM(Schedules!B135:B136) -> -423 | C17: =SUM(Schedules!C135:C136) -> -136 | D17: =SUM(Schedules!D135:D136) -> 249 | E17: =SUM(Schedules!E135:E136)+('Balance Sheet'!E25-'Balance Sheet'!D25)+'Balance Sheet'!E27-'Balance Sheet'!D27 -> -11.071392 | F17: =SUM(Schedules!F135:F136) + ('Balance Sheet'!F25-'Balance Sheet'!E25) -> 0 | G17: =SUM(Schedules!G135:G136) + ('Balance Sheet'!G25-'Balance Sheet'!F25) -> 0 | H17: =SUM(Schedules!H135:H136) + ('Balance Sheet'!H25-'Balance Sheet'!G25) -> 0 | I17: =SUM(Schedules!I135:I136) + ('Balance Sheet'!I25-'Balance Sheet'!H25) -> 0
A18: Net cash provided by/(used for) operating activities | B18: =SUM(B7,B9:B10,B12:B17) -> 3976 | C18: =SUM(C7,C9:C10,C12:C17) -> 4184 | D18: =SUM(D7,D9:D10,D12:D17) -> 4462 | E18: =SUM(E7,E9:E10,E12:E17) -> 3793.113 | F18: =SUM(F7,F9:F10,F12:F17) -> 3836.6703 | G18: =SUM(G7,G9:G10,G12:G17) -> 3846.8927 | H18: =SUM(H7,H9:H10,H12:H17) -> 3857.2838 | I18: =SUM(I7,I9:I10,I12:I17) -> 3867.8466
A20: Cash flows from investing activities
A21: Capital expenditures | B21: -1013 | C21: -1024 | D21: -801 | E21: =-Schedules!E73 -> -914.50992 | F21: =-Schedules!F73 -> -916.51337 | G21: =-Schedules!G73 -> -918.54985 | H21: =-Schedules!H73 -> -920.61995 | I21: =-Schedules!I73 -> -922.72426
A22: Other investing activities (Historical plug) | B22: =SUM(Schedules!B139:B143) -> 97 | C22: =SUM(Schedules!C139:C143) -> 1 | D22: =SUM(Schedules!D139:D143) -> -1032 | E22: =SUM(Schedules!E139:E143) -> 0 | F22: =SUM(Schedules!F139:F143) -> 0 | G22: =SUM(Schedules!G139:G143) -> 0 | H22: =SUM(Schedules!H139:H143) -> 0 | I22: =SUM(Schedules!I139:I143) -> 0
A23: Net cash provided by/(used for) investing activities | B23: =SUM(B21:B22) -> -916 | C23: =SUM(C21:C22) -> -1023 | D23: =SUM(D21:D22) -> -1833 | E23: =SUM(E21:E22) -> -914.50992 | F23: =SUM(F21:F22) -> -916.51337 | G23: =SUM(G21:G22) -> -918.54985 | H23: =SUM(H21:H22) -> -920.61995 | I23: =SUM(I21:I22) -> -922.72426
A25: Cash flows from financing activities
A26: Repayments of long-term debt | B26: -848 | C26: -618 | D26: -678 | E26: =Schedules!E90 -> -1900 | F26: =Schedules!F90 -> 0 | G26: =Schedules!G90 -> 0 | H26: =Schedules!H90 -> 0 | I26: =Schedules!I90 -> 0
A27: Proceeds from issuance of long-term debt | B27: 657 | C27: 594 | D27: 1620 | E27: =Schedules!E89 -> 1900 | F27: =Schedules!F89 -> 0 | G27: =Schedules!G89 -> 0 | H27: =Schedules!H89 -> 0 | I27: =Schedules!I89 -> 0
A28: Proceeds from issuance of commercial paper | B28: 150 | C28: 0 | D28: 0 | E28: 0 | F28: =E28 -> 0 | G28: =F28 -> 0 | H28: =G28 -> 0 | I28: =H28 -> 0
A29: Repayments of commercial paper | B29: -150 | C29: 0 | D29: 0 | E29: 0 | F29: =E29 -> 0 | G29: =F29 -> 0 | H29: =G29 -> 0 | I29: =H29 -> 0
A30: Dividends paid | B30: -1965 | C30: -1931 | D30: -1898 | E30: =Schedules!E119 -> -1906 | F30: =E30 -> -1906 | G30: =F30 -> -1906 | H30: =G30 -> -1906 | I30: =H30 -> -1906
A31: Other financing activities (Historical plug) | B31: =SUM(Schedules!B146:B147) -> -522 | C31: =SUM(Schedules!C146:C147) -> -1053 | D31: =SUM(Schedules!D146:D147) -> -295 | E31: =SUM(Schedules!E146:E147) -> 0 | F31: =SUM(Schedules!F146:F147) -> 0 | G31: =SUM(Schedules!G146:G147) -> 0 | H31: =SUM(Schedules!H146:H147) -> 0 | I31: =SUM(Schedules!I146:I147) -> 0
A32: Net cash provided by/(used for) financing activities | B32: =SUM(B26:B31) -> -2678 | C32: =SUM(C26:C31) -> -3008 | D32: =SUM(D26:D31) -> -1251 | E32: =SUM(E26:E31) -> -1906 | F32: =SUM(F26:F31) -> -1906 | G32: =SUM(G26:G31) -> -1906 | H32: =SUM(H26:H31) -> -1906 | I32: =SUM(I26:I31) -> -1906
A34: Effect of exchange rate changes on cash | B34: -19 | C34: -71 | D34: 80 | E34: 0 | F34: =E34 -> 0 | G34: =F34 -> 0 | H34: =G34 -> 0 | I34: =H34 -> 0
A35: Net increase/(decrease) in cash, cash equivalents, and restricted cash | B35: 363 | C35: 82 | D35: 1458 | E35: =SUM(E18,E23,E32,E34) -> 972.60307 | F35: =SUM(F18,F23,F32,F34) -> 1014.1569 | G35: =SUM(G18,G23,G32,G34) -> 1022.3428 | H35: =SUM(H18,H23,H32,H34) -> 1030.6639 | I35: =SUM(I18,I23,I32,I34) -> 1039.1224
A36: Balance at beginning of period | B36: 1041 | C36: =B37 -> 1404 | D36: =C37 -> 1486 | E36: =D37 -> 2944 | F36: =E37 -> 3916.6031 | G36: =F37 -> 4930.76 | H36: =G37 -> 5953.1028 | I36: =H37 -> 6983.7667
A37: Balance at end of period | B37: =SUM(B35:B36) -> 1404 | C37: =SUM(C35:C36) -> 1486 | D37: =SUM(D35:D36) -> 2944 | E37: =SUM(E35:E36) -> 3916.6031 | F37: =SUM(F35:F36) -> 4930.76 | G37: =SUM(G35:G36) -> 5953.1028 | H37: =SUM(H35:H36) -> 6983.7667 | I37: =SUM(I35:I36) -> 8022.889
